README.md
setup.py
faber/__init__.py
faber/cli.py
faber/dataio.py
faber/faber.py
faber/utils.py
faber/example_project/__init__.py
faber/example_project/connectors.py
faber/example_project/src/__init__.py
faber/example_project/src/data_engineering/__init__.py
faber/example_project/src/data_engineering/fea/__init__.py
faber/example_project/src/data_engineering/int/__init__.py
faber/example_project/src/data_engineering/master/__init__.py
faber/example_project/src/data_engineering/raw/__init__.py
faber/example_project/src/data_science/__init__.py
faber_ml.egg-info/PKG-INFO
faber_ml.egg-info/SOURCES.txt
faber_ml.egg-info/dependency_links.txt
faber_ml.egg-info/entry_points.txt
faber_ml.egg-info/top_level.txt