Metadata-Version: 2.1
Name: faber-ml
Version: 0.0.6
Summary: Quick start ml experimentation pipelines
Home-page: UNKNOWN
Author: Bradley Nobbs
Author-email: bradleynobbs@gmail.com
License: UNKNOWN
Platform: UNKNOWN
Classifier: Programming Language :: Python :: 3
Classifier: License :: OSI Approved :: MIT License
Classifier: Operating System :: OS Independent
Requires-Python: >=3.6
